see2sound/__init__.py
see2sound/audio_similarity.py
see2sound/evaluation.py
see2sound/inference.py
see2sound/version.py
see2sound/codi/__init__.py
see2sound/codi/cfg_helper.py
see2sound/codi/cfg_holder.py
see2sound/codi/sync.py
see2sound/codi/common/__init__.py
see2sound/codi/common/registry.py
see2sound/codi/common/utils.py
see2sound/codi/models/__init__.py
see2sound/codi/models/codi.py
see2sound/codi/models/ema.py
see2sound/codi/models/model_module_infer.py
see2sound/codi/models/sd.py
see2sound/codi/models/common/__init__.py
see2sound/codi/models/common/get_model.py
see2sound/codi/models/common/get_optimizer.py
see2sound/codi/models/common/get_scheduler.py
see2sound/codi/models/common/utils.py
see2sound/codi/models/ddim/__init__.py
see2sound/codi/models/ddim/ddim.py
see2sound/codi/models/ddim/ddim_vd.py
see2sound/codi/models/ddim/diffusion_utils.py
see2sound/codi/models/encoders/__init__.py
see2sound/codi/models/encoders/clap.py
see2sound/codi/models/encoders/clip.py
see2sound/codi/models/encoders/clap_modules/__init__.py
see2sound/codi/models/encoders/clap_modules/open_clip/__init__.py
see2sound/codi/models/encoders/clap_modules/open_clip/bert.py
see2sound/codi/models/encoders/clap_modules/open_clip/factory.py
see2sound/codi/models/encoders/clap_modules/open_clip/feature_fusion.py
see2sound/codi/models/encoders/clap_modules/open_clip/htsat.py
see2sound/codi/models/encoders/clap_modules/open_clip/linear_probe.py
see2sound/codi/models/encoders/clap_modules/open_clip/loss.py
see2sound/codi/models/encoders/clap_modules/open_clip/model.py
see2sound/codi/models/encoders/clap_modules/open_clip/openai.py
see2sound/codi/models/encoders/clap_modules/open_clip/pann_model.py
see2sound/codi/models/encoders/clap_modules/open_clip/pretrained.py
see2sound/codi/models/encoders/clap_modules/open_clip/timm_model.py
see2sound/codi/models/encoders/clap_modules/open_clip/tokenizer.py
see2sound/codi/models/encoders/clap_modules/open_clip/transform.py
see2sound-0.1.1.dist-info/LICENSE
see2sound-0.1.1.dist-info/METADATA
see2sound-0.1.1.dist-info/WHEEL
see2sound-0.1.1.dist-info/top_level.txt
see2sound-0.1.1.dist-info/RECORD
