Metadata-Version: 2.1
Name: see2sound
Version: 0.1.1
Summary: SEE-2-SOUND: Zero-Shot Spatial Environment-to-Spatial Sound
Home-page: https://github.com/see2sound/see2sound
Author: Rishit Dagli, Shivesh Prakash
Author-email: rishit.dagli@gmail.com
License-File: LICENSE
Provides-Extra: dev
Requires-Dist: check-manifest ; extra == 'dev'
Requires-Dist: twine ; extra == 'dev'
Requires-Dist: ruff ; extra == 'dev'
